hulin_mcp_server/__init__.py
hulin_mcp_server/新建文本文档.txt
hulin_mcp_server-1.1.0.dist-info/WHEEL
hulin_mcp_server-1.1.0.dist-info/entry_points.txt
hulin_mcp_server-1.1.0.dist-info/METADATA
hulin_mcp_server-1.1.0.dist-info/RECORD
