Metadata-Version: 2.3
Name: hulin-mcp-server
Version: 1.1.0
Summary: this is my test function,add two number and return result
Requires-Dist: mcp[cli]>=1.12.4
Requires-Python: >=3.13
